relativePathImport/__init__.py
relativePathImport/relativePathImport.py
relativePathImport-0.2.8.dist-info/METADATA
relativePathImport-0.2.8.dist-info/WHEEL
relativePathImport-0.2.8.dist-info/top_level.txt
relativePathImport-0.2.8.dist-info/RECORD
