Metadata-Version: 2.2
Name: relativePathImport
Version: 0.2.8
Summary: The `relativePathImport` class provides various utilities to handle paths in a project and allows you to work with relative paths, navigate backwards in the directory structure, and import modules from relative file locations. It works for both windows and linux.
Home-page: https://github.com/brighamturner12/relativePathImport.git
Author: Brigham Turner
Author-email: brighamturner@narratebay.com
License: MIT
Project-URL: Documentation, https://github.com/brighamturner12/relativePathImport/blob/main/readme.md
Project-URL: Source Code, https://github.com/brighamturner12/relativePathImport/blob/main/importRelative_source.py
Classifier: Programming Language :: Python :: 3
Classifier: License :: OSI Approved :: MIT License
Classifier: Operating System :: OS Independent
Requires-Python: >=3.6
Dynamic: author
Dynamic: author-email
Dynamic: classifier
Dynamic: description
Dynamic: description-content-type
Dynamic: home-page
Dynamic: license
Dynamic: project-url
Dynamic: requires-python
Dynamic: summary
